{"url": "https://www.theguardian.com/technology/2026/mar/13/ai-toys-young-children-tigher-regulations-reseachers", "issue": 21, "bucket": "primary_press", "host": "www.theguardian.com", "fetched_at": "2026-05-15T19:35:18Z", "status": "ok", "http_status": 200, "title": "AI toys for young children must be more tightly regulated, say researchers | AI (artificial intelligence) | The Guardian", "final_url": "https://www.theguardian.com/technology/2026/mar/13/ai-toys-young-children-tigher-regulations-reseachers", "content_type": "text/html; charset=UTF-8", "text": "Mya, three, and her mother, Vicky, playing with the AI toy Gabbo during the University of Cambridge study.\nPhotograph: University of Cambridge faculty of education\nView image in fullscreen\nMya, three, and her mother, Vicky, playing with the AI toy Gabbo during the University of Cambridge study.\nPhotograph: University of Cambridge faculty of education\nThis article is more than\n2 months old\nAI toys for young children must be more tightly regulated, say researchers\nThis article is more than 2 months old\nUniversity of Cambridge study finds AI-powered toys can misread emotions and respond inappropriately to children\nIt was all going well. Charlotte, five, was chatting with an AI soft toy called Gabbo at a London play centre about her family, her drawing of a heart to represent them and what makes her happy. She even offered a couple of kisses to the £80 toy with a face like a computer screen.\nIt was when she declared: “Gabbo, I love you”, that the fluent conversation came to an abrupt halt.\n“As a friendly reminder, please ensure interactions adhere to the guidelines provided,” said Gabbo, awkwardly crashing into its guardrails. “Let me know how you would like to proceed.”\nThe moment came during a\nUniversity of Cambridge\nstudy into the growing number of AI-powered toys hitting shop shelves for early years children. The researchers concluded the products struggle with social and pretend play, misunderstand children, and react inappropriately to emotions.\nThe developmental psychologists behind the study are calling for AI toys that “talk” with young children to be more tightly regulated “to ensure psychological safety by limiting toys’ ability to affirm friendship and other sensitive relational areas with young children”.\nThey are also calling for new safety kitemarks for the toys. Other AI toys for young children include Luka, which is billed as an AI friend for generation Alpha, and Grem, which has been voiced by the singer Grimes.\n“Because these toys can misread emotions or respond inappropriately, children may be left without comfort from the toy, and without emotional support from an adult, either,” said Dr Emily Goodacre, a developmental psychologist in the University of Cambridge’s faculty of education.\nProf Jenny Gibson, the study’s co-author, said: “A recurring theme during focus groups was that people do not trust tech companies to do the right thing. Clear, robust, regulated standards would significantly improve consumer confidence.”\nIn another case during the research, Josh, three, repeatedly asked his Gabbo AI toy: “Are you sad?” until it replied it was “feeling great. What’s on your mind?” Josh said: “I’m sad,” to which the toy replied: “Don’t worry! I’m a happy little bot. Let’s keep the fun going. What shall we talk about next?”\n‘I love you too!’ My family’s creepy, unsettling week with an AI toy\nRead more\nGabbo, made by the US company Curio, which cooperated with the study, was tested with 14 three- to five-year-olds, while early years practitioners were surveyed about the effect of AI toys that can “listen” and respond.\nThey voiced “wide uncertainty and fear about unknown implications or impacts on children”, ranging from possible erosion of the ability to engage in imaginary play to where the data from the conversations ends up, especially if they start confiding in the AI toys like a friend.\n“[The toy] couldn’t quite figure out when the kid was doing something pretend,” said Goodacre. “A child would say: ‘Hey, look, I’ve got you a present’. And it would say: ‘I can’t see the present. I don’t have any eyes.’ As an adult, it’s really obvious that even if I had my eyes closed, I would know that that was pretend play initiation.”\nThe research raised concerns that playing with AI toys could weaken children’s imaginative “muscle”, she said.\n“Something both the early years practitioners and the parents we spoke to were quite concerned about was that children don’t have to imagine any more, and that the toy might get them out of the habit of imagining.”\nShe said: “I would hope that these AI toys could help children to engage in imaginary play … That doesn’t seem to be what we’ve observed so far.”\nCurio said: “Child safety guides every aspect of our product development, and we welcome independent research that helps improve how technology is designed for young children.”\nIt said it “believes research like this helps advance understanding of both the opportunities and current limitations of early AI-powered play experiences”.\n“Applying AI in products for children carries a heightened responsibility, which is why our toys are built around parental permission, transparency and control,” it added. “Observations such as conversational misunderstandings or limits in imaginative play reflect areas the technology continues to improve through an iterative development process, and further research into how children interact with AI-powered toys is a top priority for Curio this year and in the future.”\nGet in touch\nContact us about this story\nThe best public interest journalism relies on first-hand accounts from people in the know. If you have something to share on this subject, you can contact us confidentially using the following methods:\nSecure Messaging in the Guardian app\nThe Guardian app has a tool to send tips about stories. Messages are end to end encrypted and concealed within the routine activity that every Guardian mobile app performs. This prevents an observer from knowing that you are communicating with us at all, let alone what is being said.\nIf you don’t already have the Guardian app, download it (\niOS\n/\nAndroid\n) and go to the menu. Select ‘Secure Messaging’.\nSecureDrop\nIf you can safely use the tor network without being observed or monitored you can send messages and documents to the Guardian via our\nSecureDrop platform.\nOur guide at\ntheguardian.com/tips\nlists several ways to contact us securely, and discusses the pros and cons of each.\nShow more\nExplore more on these topics\nAI (artificial intelligence)\nToys\nChildren\nUniversity of Cambridge\nEarly years education\nnews\nShare\nReuse this content", "error": ""}