{"url": "https://variety.com/2026/film/global/filmax-dinogames-carlos-f-de-vigo-european-film-market-1236660806/", "issue": 19, "bucket": "industry_trade", "host": "variety.com", "fetched_at": "2026-05-15T19:35:43Z", "status": "ok", "http_status": 200, "title": "Filmax Takes Sales on 'DinoGames,' Unveils First Images", "final_url": "https://variety.com/2026/film/global/filmax-dinogames-carlos-f-de-vigo-european-film-market-1236660806/", "content_type": "text/html; charset=UTF-8", "text": "Feb 12, 2026 9:45pm PT\nFilmax Boards AI-Driven 3D ‘DinoGames’ for EFM\nBy\nEmiliano De Pablos\nPlus Icon\nEmiliano De Pablos\nLatest\nSpanish Sellers Ride Cannes Momentum\n2 days ago\nSantiago Segura and Sony, Plus a Little Help From Alec Baldwin and Kevin Spacey, Smash Spanish Cinema Records With ‘Torrente for President’\n2 months ago\nZDF Studios Snags ‘Ancient Superstructures’ Season 4 Rights, Featuring the Completion of Iconic Barcelona Landmark, the Sagrada Familia (EXCLUSIVE)\n3 months ago\nSee All\nDinoGames Courtesy of Filmax\nFilmax\nhas taken international sales rights to “\nDinoGames\n,” a 3D-animated feature directed by Goya winners Carlos F. de Vigo and Lorena Ares, with the Barcelona-based company set to present first images to buyers at Berlin’s European Film Market.\nProduced by Spain’s Dr. Platypus & Ms. Wombat alongside Belgian producer Beside, “DinoGames” is positioned as a family adventure fusing video-game wish fulfilment with a contemporary AI hook.\nRelated Stories\nJordan Firstman Sobs and Kisses Co-Star Diego Calva as 'Club Kid' Becomes Cannes' First Breakout Hit of 2026 and Earns a 6-Minute Standing Ovation\nJordana Brewster on Bringing ‘Fast & Furious’ to Cannes for Its 25th Anniversary and Honoring Paul Walker With ‘Fast Forever’: 'We've All Got Each Other's Backs, No Matter What'\nThe project has already enjoyed early market traction, surfacing on the international industry circuit at Annecy’s MIFA Pitch and across Cartoon’s flagship platforms, Cartoon Movie and Cartoon Forum.\nPopular on Variety\nSet inside the world’s most popular video game, the film imagines a next-gen AI system that allows in-game characters to become sentient, shifting the game from entertainment into a living universe that awakens, evolves and begins interacting with human beings.\nThe story is driven by siblings Codi (10) and Vera (15), still reeling one year after their mother Loren vanishes during a mysterious accident at her hi-tech lab.\nThe lab was developing a revolutionary AI Universe Simulator for the DinoGames ecosystem. When Codi receives an invitation to test the simulator’s latest build, the message turns out to be a trap set by Pinkolaf, a vengeful AI creature born inside DinoGames that has learned to manipulate real-world electronics.\nA system error pulls Codi, Vera, their friends and Aunt Susan into the game world, while Danny is left behind in the damaged lab, racing to reopen a portal as both realities tilt toward a final showdown.\nScript development is led by Todd Edwards, a key writer on indie breakout “Hoodwinked,” while character design is by Annie Award-winner Carlos Grangel, behind characters for filmmakers such as Guillermo del Toro. Animatics include work by Paco Sáez and David Frasquet.\nThe feature has been supported by pubcaster RTVE, Spain’s Ministry of Culture, Eurimages, and regional partners including Sodena and Generazinema in Navarre, Ourense Provincial Council and Wallonia’s Wallimage.\n“This is the adventure of fantasy and friendship we were all dreaming of seeing on the big screen,” Ares said. De Vigo added: “What happens when the code awakens?”\nFilmax international head Iván Díaz called the pickup “a strategic move for Berlin and one which we’ve developed very closely with its producers.”\nJump to Comments\nMore from Variety\n‘Harry Potter’ Series Is ‘A Lot of Pressure’ but It’s ‘Very Special,’ Says HBO Max Exec: ‘The World That Has Been Created Is Absolutely Extraordinary’\nDuffy to Speak About Sexual Assault, Kidnapping and Absence From Music for First Time in Disney+ Documentary\n‘Getting Under Your Skin’ Undercover Drama Greenlit for Second Season (EXCLUSIVE)\n‘In Treatment’ Creator Hagai Levi Makes a Case for ‘Arthouse Television’ With ‘Etty,’ Talks Cultural Boycott of Israel\nCouncil of Europe’s Alain Berset Talks ‘First Ever’ Convention on the Co-Production of Audiovisual Works in the Form of Series: ‘We Hope It Will Be Possible to Develop This Really Rapidly’\n‘Ghosts’ Season 2 Confirmed for Germany as BBC Studios Highlights Global Success of Sitcom Format\nLoading comments...", "error": ""}