{"url": "https://variety.com/2025/film/news/ai-powered-cinematic-universe-platform-engen3-1236543349/", "issue": 2, "bucket": "industry_trade", "host": "variety.com", "fetched_at": "2026-05-15T19:35:25Z", "status": "ok", "http_status": 200, "title": "AI-Powered Cinematic Universe Platform enGEN3 Launched", "final_url": "https://variety.com/2025/film/news/ai-powered-cinematic-universe-platform-engen3-1236543349/", "content_type": "text/html; charset=UTF-8", "text": "Oct 9, 2025 12:00am PT\nAI-Powered Cinematic Universe Platform enGEN3 Launched by Goldfinch, The Squad (EXCLUSIVE)\nBy\nNaman Ramachandran\nPlus Icon\nNaman Ramachandran\nLatest\nHamaguchi’s French Debut ‘All of a Sudden’ Stuns Cannes With 7-Minute Ovation, Longest of the Fest So Far\n4 hours ago\n‘The Napa Boys’ Heads to Cannes Film Market as Mise-En-Scène Company Launches International Sales (EXCLUSIVE)\n8 hours ago\nParis Outfit Pavo Films Launches With Gurvinder Singh’s ‘Rehmat,’ Starring Naseeruddin Shah (EXCLUSIVE)\n10 hours ago\nSee All\nenGEN3\nTwo entertainment companies are betting that artificial intelligence can help independent filmmakers compete with major studios in building expansive story worlds.\nGoldfinch\nand\nThe Squad\nhave unveiled\nenGEN3\n, a jointly owned platform that uses\nAI\nto help creators develop cinematic universes while managing IP rights and revenue sharing with fans. The venture aims to democratize tools typically available only to large studios, enabling filmmakers to expand stories across multiple media formats.\nRelated Stories\nIsabelle Huppert on the Mystery of Asghar Farhadi’s 'Parallel Tales,' Cannes and Why 'Hollywood Remains Hollywood'\nEight Directors, Five Countries, Four Films: Inside KawanKawan Media's 'Next Step Studio Indonesia' at Cannes\n“enGEN3 gives filmmakers studio-level tools to build cinematic universes with fan participation, extending their stories seamlessly across film, games, print, and beyond,” said Jordan Bayne, founder of The Squad and enGEN3.\nPopular on Variety\nThe platform’s first project is “By Blood & By Bone,” a sci-fi anime feature pilot from writer Dave Kebo. The film integrates two Web3 anime collections – Ordinauts on Bitcoin and Oni Force on Ethereum – in what the companies describe as a new model for community-driven storytelling.\n“With ‘By Blood & By Bone,’ we’re bringing community storytelling into an epic anime series while creating a model for IP ownership and monetization that benefits both creators and fans,” said Kebo.\nHenry Finn, CEO of Oni Force, added: “This is the next chapter in storytelling: ownership and imagination shared by all.”\nThe venture taps experienced tech and creative talent. CTO Doug Thompson previously held roles at gaming and AI companies including Remedy and Sojen. Creative director HaZ Dulull has directed for Disney+ and contributed to video game projects including “Dune: Awakening” and Fortnite. He runs transmedia studio Beyond The Pixels.\nA Q1 2026 full launch is targeted for enGEN3, with beta access coming sooner. The companies plan to roll out more projects and tools next year, drawing from Goldfinch’s catalog of hundreds of financed productions.\n“At Goldfinch, we back bold visions for the future of entertainment,” said Phil McKenzie, co-founder of Goldfinch. “Jordan pioneered the Film3 model, and enGEN3 represents the next evolution – a way for creators and fans to connect through both creation and distribution.”\nGoldfinch has backed more than 300 projects since its 2014 founding and has won Academy Awards and BAFTAs. The Squad focuses on projects blending cinema with generative AI and Web3 technology under what it calls the Film3 framework – emphasizing creator ownership and audience participation in storytelling.\nJump to Comments\nMore from Variety\nEuropean Scripted TV Production on Downward Trend as Shorter Seasons and Episode Runtimes Define New Normal\nAmazon MGM Studios’ ‘The Glass House’ Premiere Breaks New Ground as Series Mania Closing Gala (EXCLUSIVE)\nCouncil of Europe’s Alain Berset Talks ‘First Ever’ Convention on the Co-Production of Audiovisual Works in the Form of Series: ‘We Hope It Will Be Possible to Develop This Really Rapidly’\nDark and Quaint Crime Dramedy ‘Welcome to Kingston-Falls,’ From Robin Aubert, Premieres at Series Mania’s International Panorama\nGlobal Constellation Boards Haunting Indonesia-Set Drama ‘Heaven’s Gate’ (EXCLUSIVE)\nRussell T Davies Says New Show ‘Tip Toe’ Is a ‘Reaction to Where Politics Is Heading’: ‘Queer Discourse’ Has Become ‘So Dangerous in a Way I Never Thought Would Happen Again’\nLoading comments...", "error": ""}