{"url": "https://deadline.com/2026/04/google-cloud-avid-ai-editing-partnership-1236863217/", "issue": 26, "bucket": "industry_trade", "host": "deadline.com", "fetched_at": "2026-05-15T19:35:52Z", "status": "ok", "http_status": 200, "title": "Google Cloud And Avid Join Forces To Inject AI Into Video Editing Process", "final_url": "https://deadline.com/2026/04/google-cloud-avid-ai-editing-partnership-1236863217/", "content_type": "text/html; charset=UTF-8", "text": "The Google Cloud logo\nPhoto by Joan Cros/NurPhoto via Getty Images\nGoogle Cloud\nhas set a multi-year partnership with\nAvid\nas the companies look to add generative and agentic\nAI\ntools to the video\nediting\nprocess.\nThe team-up was announced ahead of Saturday’s start of the\nNAB Show\nin Las Vegas, where both companies will have a significant presence.\nAs part of the agreement, Google’s Gemini models and Vertex AI will be incorporated directly into Avid’s setup, which the companies say will significantly reduce the time required for media discovery and production. Avid will add the Google AI to Media Composer, its non-linear editing system for professional film and TV; and Content Core, a new cloud-native, software-as-a-service platform.\nRelated Stories\nFestivals\nHow Putting Their Hopes In A 'Space Unicorn' Has Brother Duo Evan & Gregg Spiridellis Heading To Market In Cannes\nNews\nMeet Wonder Studios, The $50M British Studio Striving To Become The A24 Of AI Production\nIn a blog post, Google Cloud said recent clients have included major local TV station owner Gray Media; Major League Baseball; and NBCUniversal.\nWatch on Deadline\nAlong with new programming, the blog post observed, “media organizations sit on decades of archived footage that is difficult to search through and expensive to manage. AI can automatically tag every scene and shot, making massive video libraries as searchable as the web. This helps teams find and reuse content in seconds, opening up new ways to monetize archives through hyper-local streaming and more relevant viewer experiences.”\nFrance’s Canal+ is one recent media player to\nincorporate Google’s AI tools\nto help organize its archives.\nIn an interview with Deadline, Buzz Hays, a film producer and former Lucasfilm exec who is now Google Cloud’s Global Market Lead Entertainment Industry, said the potential of mining libraries is vast. With so much investment in original microdramas, for example, IP holders could use the technology being brought to market by Google Cloud and Avid to repackage library series.\n“In a half-hour, 22-minute comedy series, there are seven acts, because an act was considered that chunk between commercials,” Hays noted. “So you already have the ability to take a series and turn it into a micro series that you wanted to. … It’s a very interesting possibility, especially given how expensive content production has gotten.”\nAvid CEO Wellford Dillard said the company’s customers “are asking for intelligent tools that plug into existing workflows and scale with their creativity.” The Google Cloud partnership is helping meet that need, and it “strengthens our ability to deliver secure, AI-driven innovation–while keeping Avid interoperable and adaptable across the broader production landscape,” Dillard added.\nAnil Jain, global managing director of strategic industries for Google Cloud, said the collaboration signals that the industry is “moving beyond simple automation.” An editor accessing the AI-infused Avid tools “can now collaborate with an intelligent agent to create assets on the fly and handle the heavy lifting of matching styles and filling timelines, enabling them to focus on storytelling instead of infrastructure.”\nMust Read Stories\nHide Articles\nSam Raimi To Helm ‘Magic’ For Lionsgate, Redo Of 1978 Ventriloquist Horror Pic\n‘Club Kid’ & ‘All Of A Sudden’ Are Fest’s First Big Buzz Films; Reviews & Red Carpet\n‘Obsession’ Consumes $2.6M In Previews; ‘Hail Mary’ Tops ‘Oppenheimer’\nFrancis Lawrence Eyeing To Direct Supernatural Thriller ‘Carry Me To My Grave’\nRead More About:\n1 Comments\nSubscribe to Deadline\nGet our Breaking News Alerts and Keep your inbox happy.\nSign Up\n1 Comment\nCancel reply\nSubmit a comment\nAnonymous\non April 17, 2026 1:02 pm\njfc the guy Google has leading the team incorporating the entertainment industry into it’s AI, thinks there are 7(!) acts in a half hour sitcom, we are in some big trouble.\nReply\nReply to", "error": ""}