{"url": "https://www.digitaltrends.com/gaming/xbox-ally-x-gets-its-own-dlss-rivaling-frame-upscaling-tech-among-other-updates/", "issue": 28, "bucket": "other", "host": "www.digitaltrends.com", "fetched_at": "2026-05-15T19:34:45Z", "status": "ok", "http_status": 200, "title": "Xbox Ally X gets its own DLSS-rivaling frame upscaling tech, among other updates - Digital Trends", "final_url": "https://www.digitaltrends.com/gaming/xbox-ally-x-gets-its-own-dlss-rivaling-frame-upscaling-tech-among-other-updates/", "content_type": "text/html; charset=UTF-8", "text": "Microsoft\njust dropped one of the most meaningful updates for the ROG Xbox Ally and\nAlly X\n. The latter is also getting Auto SR, Xbox’s AI-powered upscaling technology, as a preview for\nXbox\nInsiders, starting today.\nFor those catching up, Auto SR, short for Automatic Super Resolution, operates at the Windows OS level rather than requiring developers to add it to individual games. This means that any DirectX 11 or DirectX 12 title can potentially benefit from the technology, without an additional patch.\nXbox\nWhat is Auto SR, and why does it matter?\nWhen docked, Auto SR uses the\nAlly X’s dedicated NPU\n, found only in its Ryzen AI Z2 Extreme chip, not the base Ally, to upscale games to 1440p-like detail while running at a lower native resolution.\nRecommended Videos\nPer the early GDC 2026 demos, the technology could bring up to a 30% drame rate improvement on supported titles. Some latency is introduced, though Microsoft considers it worthwhile. Support for portable mode is also being explored.\nAs part of the new update, docking gets significantly smarter for both models, as they auto-disable the handheld display when connected to a TV. Compatible\nsmart TVs\nwill also activate low-latency gaming modes automatically.\nXbox\nWhat other updates are rolling out to the handheld consoles?\nWhile the ROG 100 Charger Dock gets HDR10, the ROG Bulwark Dock gets both HDR10 and\nVRR\n(which synchronizes the TV’s refresh rate to the game’s frame rate in real-time). Bluetooth LE Audio also makes its debut, bringing lower-latency wireless audio and high-fidelity voice chat to both modes.\nThe update also refines haptic feedback across the board. Rounding things out is a Collective Library update that brings games installed from any PC store, including Steam, Epic, and others, directly to the Xbox library via a ‘+’ button. This means that users can launch everything from one unified interface without bouncing between apps.", "error": ""}