{"url": "https://github.com/hao-ai-lab/FastVideo", "issue": 21, "bucket": "academic", "host": "github.com", "fetched_at": "2026-05-15T19:37:46Z", "status": "ok", "http_status": 200, "title": "GitHub - hao-ai-lab/FastVideo: A unified inference and post-training framework for accelerated video generation. · GitHub", "final_url": "https://github.com/hao-ai-lab/FastVideo", "content_type": "text/html; charset=utf-8", "text": "|\nDocumentation\n|\nQuick Start\n|\nWeekly Dev Meeting\n| 🟣💬\nSlack\n|  🟣💬\nWeChat\n|\nFastVideo is a unified post-training and real-time inference framework for accelerated video generation.\nNEWS\n2026/03/17\n: Release Live demo:\nInto the Dreamverse: Vibe Directing in FastVideo\n, check out the\nBlog\n.\n2026/03/13\n: Release Live demo:\nCreate a 5s 1080p Video in 4.5s with FastVideo on a Single GPU\n, check out the\nBlog\n.\n2025/11/19\n: Release\nCausalWan2.2 I2V A14B Preview\nmodels,\nBlog\nand\nInference Code!\n.\n2025/08/04\n: Release\nFastWan\nmodels and\nSparse-Distillation\n.\nMore News\n2025/06/14\n: Release finetuning and inference code for\nVSA\n.\n2025/04/24\n:\nFastVideo V1\nis released!\n2025/02/18\n: Release the inference code for\nSliding Tile Attention\n.\nKey Features\nFastVideo has the following features:\nEnd-to-end post-training support for bidirectional and autoregressive models:\nSupport full finetuning and LoRA finetuning for state-of-the-art open video DiTs\nData preprocessing pipeline for video, image, and text data\nDistribution Matching Distillation (DMD2) stepwise distillation.\nSparse attention with\nVideo Sparse Attention\nSparse distillation\nto achieve >50x denoising speedup\nScalable training with FSDP2, sequence parallelism, and selective activation checkpointing.\nCausal distillation through Self-Forcing\nSee this\npage\nfor full list of supported models and recipes.\nState-of-the-art performance optimizations for inference\nSequence Parallelism for distributed inference\nMultiple state-of-the-art attention backends\nUser-friendly CLI and Python API\nSee this\npage\nfor full list of supported optimizations.\nDiverse hardware and OS support\nSupport H100, A100, 4090\nSupport Linux, Windows, MacOS\nSee this\npage\nfor full list of supported models, hardware assumptions, and optimization compatibility.\nGetting Started\nWe recommend using\nuv\nto create a clean environment. If you previously used Conda, switching to uv generally gives faster and more stable installs.\n#\nCreate and activate a new uv environment\nuv venv --python 3.12 --seed\nsource\n.venv/bin/activate\n#\nInstall FastVideo\nuv pip install fastvideo\nPlease see our\ndocs\nfor more detailed installation instructions.\nSparse Distillation\nFor our sparse distillation techniques, please see our\ndistillation docs\nand check out our\nblog\n.\nSee below for recipes and datasets:\nModel\nSparse Distillation\nDataset\nFastWan2.1-T2V-1.3B\nRecipe\nFastVideo Synthetic Wan2.1 480P\nFastWan2.2-TI2V-5B\nRecipe\nFastVideo Synthetic Wan2.2 720P\nInference\nGenerating Your First Video\nHere's a minimal example to generate a video using the default settings. Make sure VSA kernels are\ninstalled\n. Create a file called\nexample.py\nwith the following code:\nimport\nos\nfrom\nfastvideo\nimport\nVideoGenerator\ndef\nmain\n():\nos\n.\nenviron\n[\n\"FASTVIDEO_ATTENTION_BACKEND\"\n]\n=\n\"VIDEO_SPARSE_ATTN\"\n# Create a video generator with a pre-trained model\ngenerator\n=\nVideoGenerator\n.\nfrom_pretrained\n(\n\"FastVideo/FastWan2.1-T2V-1.3B-Diffusers\"\n,\nnum_gpus\n=\n1\n,\n# Adjust based on your hardware\n)\n# Define a prompt for your video\nprompt\n=\n\"A curious raccoon peers through a vibrant field of yellow sunflowers, its eyes wide with interest.\"\n# Generate the video\nvideo\n=\ngenerator\n.\ngenerate_video\n(\nprompt\n,\noutput_path\n=\n\"my_videos/\"\n,\n# Controls where videos are saved\nsave_video\n=\nTrue\n)\nif\n__name__\n==\n'__main__'\n:\nmain\n()\nRun the script with:\npython example.py\nFor a more detailed guide, please see our\ninference quick start\n.\nMore Guides\nDesign Overview\nDistillation Guide\nContribution Guide\nAwesome work using FastVideo or our research projects\nSGLang\n: SGLang's diffusion inference functionality is based on a fork of FastVideo on Sept. 24, 2025.\nDanceGRPO\n: A unified framework to adapt Group Relative Policy Optimization (GRPO) to visual generation paradigms. Code based on FastVideo.\nSRPO\n: A method to directly align the full diffusion trajectory with fine-grained human preference. Code based on FastVideo.\nDCM\n: Dual-expert consistency model for efficient and high-quality video generation. Code based on FastVideo.\nHY-WorldPlay\n: An action-conditioned world model model trained using FastVideo framework.\nHunyuan Video 1.5\n: A leading lightweight video generation model, where they proposed SSTA based on Sliding Tile Attention.\nKandinsky-5.0\n: A family of diffusion models for video & image generation, where their NABLA attention includes a Sliding Tile Attention branch.\nLongCat Video\n: A foundational video generation model with 13.6B parameters with block-sparse attention similar to Video Sparse Attention.\n🤝 Contributing\nWe welcome all contributions. Please check out our guide\nhere\n.\nSee details in\ndevelopment roadmap\n.\nAcknowledgement\nWe learned the design and reused code from the following projects:\nWan-Video\n,\nThunderKittens\n,\nDMD2\n,\ndiffusers\n,\nxDiT\n,\nvLLM\n,\nSGLang\n. We thank\nMBZUAI\n,\nAnyscale\n, and\nGMI Cloud\nfor their support throughout this project.\nCitation\nIf you find FastVideo useful, please consider citing our research work:\n@article\n{\nzhang2025vsa\n,\ntitle\n=\n{\nVsa: Faster video diffusion with trainable sparse attention\n}\n,\nauthor\n=\n{\nZhang, Peiyuan and Chen, Yongqi and Huang, Haofeng and Lin, Will and Liu, Zhengzhong and Stoica, Ion and Xing, Eric and Zhang, Hao\n}\n,\njournal\n=\n{\narXiv preprint arXiv:2505.13389\n}\n,\nyear\n=\n{\n2025\n}\n}\n@article\n{\nzhang2025fast\n,\ntitle\n=\n{\nFast video generation with sliding tile attention\n}\n,\nauthor\n=\n{\nZhang, Peiyuan and Chen, Yongqi and Su, Runlong and Ding, Hangliang and Stoica, Ion and Liu, Zhengzhong and Zhang, Hao\n}\n,\njournal\n=\n{\narXiv preprint arXiv:2502.04507\n}\n,\nyear\n=\n{\n2025\n}\n}", "error": ""}