{"url": "https://ai.meta.com/blog/segment-anything-model-3/?utm_source=All%20Social%20-%20Organic&utm_medium=organic_social&utm_campaign=tech_innovation_XFN&utm_term=2026&utm_content=AI%40Meta", "issue": 23, "bucket": "other", "host": "ai.meta.com", "fetched_at": "2026-05-15T19:34:37Z", "status": "http_400", "http_status": 400, "title": "", "final_url": "https://ai.meta.com/blog/segment-anything-model-3/?utm_source=All%20Social%20-%20Organic&utm_medium=organic_social&utm_campaign=tech_innovation_XFN&utm_term=2026&utm_content=AI%40Meta", "content_type": "text/html; charset=\"utf-8\"", "text": "", "error": ""}