{"url": "https://nofilmschool.com/james-cameron-ai#", "issue": 1, "bucket": "other", "host": "nofilmschool.com", "fetched_at": "2026-05-15T19:33:20Z", "status": "ok", "http_status": 200, "title": "James Cameron Says AI Is \"Never Going to Take the Place\" of Humans | No Film School", "final_url": "https://nofilmschool.com/james-cameron-ai", "content_type": "text/html; charset=utf-8", "text": "AI\nTopics\nJames Cameron Says AI Is \"Never Going to Take the Place\" of Humans\nThe director chatted about AI and\nFire and Ash\n.\nFollow us on Discover\nSee Us First on Google\nAvatar: Fire and Ash\nCredit: Disney\nJo Light\nOct 02, 2025", "error": ""}