{"url": "https://runwayml.com/BigPitchContest", "issue": 29, "bucket": "company_blog", "host": "runwayml.com", "fetched_at": "2026-05-15T19:35:01Z", "status": "ok", "http_status": 200, "title": "Runway's Big Pitch Contest for Shows that Don't Exist Yet", "final_url": "https://runwayml.com/BigPitchContest", "content_type": "text/html; charset=utf-8", "text": "Upload in progress...\nYour video file is being uploaded. The currently loaded video is the source file.\nWatch the full collection of winning pitches from Runway's inaugural Big Pitch Contest.\nThe Rules\nWhile there are no clients, there are a few rules to follow.\nRead carefully below before getting started.\nGenerated with Runway\nAll generative video must be created inside of Runway. All entrants are required to have an active Runway subscription at the time of submission.\nDuration of Pitch\nYour entry must be a single video between 1:00 and 3:00. No exceptions — anything shorter or longer will be disqualified.\nSound & music\nAudio is fair game. Music, sound design and voice over are all permitted and encouraged, so long as you have the rights. You can create audio yourself, source it or generate it.\nWatermark\nYour final pitch video must include the Big Pitch Contest watermark. You can download the watermark\nhere\n.\nOriginal work\nAll entries must be original and created specifically for this competition. Work that has been published or submitted elsewhere is not eligible. All characters and IP must be wholly owned.\nTeam size\nThere are no restrictions on team size. You can enter alone or collaborate with as many people as you like. Prizes will be awarded to team leaders.\nBe respectful and have fun\nThere is no specific genre but any offensive, graphic or explicit content will be disqualified. Read the full terms and conditions\nhere\n.\nThe Prizes\nGrand Prize – $50,000\nThe best pitch of the competition takes home the top prize. One winning pitch that will be judged on concept, craft, impact and how well the work answers the brief.\nSecond Place – $15,000\nAwarded to the runner-up entry.\nThird Place – $10,000\nAwarded to the third-place entry.\nFourth Place – $5,000\nAwarded to the fourth-place entry.\nFifth Place – $5,000\nAwarded to the fifth-place entry.\n6th-20th Place – $1,000 each\nThe next fifteen finalists each receive $1,000 to recognize the strongest work across the full field of entries.\nThe Criteria\nConcept\nThe most important criteria is your idea. How original, insightful and interesting is it?\nCraft\nHow well did you leverage Runway to bring your idea to life?\nImpact\nDoes it leave an impression on the viewer? Does it have a memorable quality to it?", "error": ""}